pydantic2ts/__init__.py
pydantic2ts/cli/__init__.py
pydantic2ts/cli/script.py
pydantic_to_typescript2-1.0.6.dist-info/LICENSE.md
pydantic_to_typescript2-1.0.6.dist-info/METADATA
pydantic_to_typescript2-1.0.6.dist-info/WHEEL
pydantic_to_typescript2-1.0.6.dist-info/entry_points.txt
pydantic_to_typescript2-1.0.6.dist-info/top_level.txt
pydantic_to_typescript2-1.0.6.dist-info/RECORD
