Metadata-Version: 2.1
Name: pydantic-to-typescript2
Version: 1.0.6
Summary: Convert pydantic v1 and pydantic v2 models to typescript interfaces
Home-page: https://github.com/dariuslabs/pydantic-to-typescript2
Author: Phillip Dupuis, Darius Labs
Author-email: sean@dariuslabs.com
License: MIT
Keywords: pydantic pydantic2 typescript annotations validation interface
Platform: UNKNOWN
Classifier: Development Status :: 5 - Production/Stable
Classifier: License :: OSI Approved :: MIT License
Classifier: Programming Language :: Python
Classifier: Programming Language :: Python :: 3
Classifier: Programming Language :: Python :: 3 :: Only
Classifier: Programming Language :: Python :: 3.8
Classifier: Programming Language :: Python :: 3.9
Classifier: Programming Language :: Python :: 3.10
Classifier: Programming Language :: Python :: 3.11
Classifier: Programming Language :: Python :: 3.12
License-File: LICENSE.md
Requires-Dist: pydantic
Provides-Extra: dev
Requires-Dist: pytest; extra == "dev"
Requires-Dist: pytest-cov; extra == "dev"
Requires-Dist: coverage; extra == "dev"
